{
  "updated_at": "2026-05-27T15:59:47Z",
  "commits": [
    {
      "hash": "b1ba5dd",
      "type": "fix",
      "message": ": read Kapso platform webhook event type from X-Webhook-Event header",
      "repo": "agendate-ya",
      "repo_display": "AgendateYa",
      "timestamp": "2026-05-27T12:59:32-03:00"
    },
    {
      "hash": "2e34510",
      "type": "feat",
      "message": ": open onboarding in popup",
      "repo": "agendate-ya-admin",
      "repo_display": "AgendateYa Admin",
      "timestamp": "2026-05-27T12:46:58-03:00"
    },
    {
      "hash": "a00a3e8",
      "type": "feat",
      "message": ": open onboarding in popup",
      "repo": "agendate-ya-admin",
      "repo_display": "AgendateYa Admin",
      "timestamp": "2026-05-27T12:41:51-03:00"
    },
    {
      "hash": "5f39e4c",
      "type": "chore",
      "message": "Update application properties open ai opt to use ENV",
      "repo": "agendate-ya",
      "repo_display": "AgendateYa",
      "timestamp": "2026-05-27T12:38:10-03:00"
    },
    {
      "hash": "811a713",
      "type": "feat",
      "message": ": brand Kapso onboarding page with es language and Veinticuatro7 theme",
      "repo": "agendate-ya",
      "repo_display": "AgendateYa",
      "timestamp": "2026-05-27T12:16:58-03:00"
    },
    {
      "hash": "9e66342",
      "type": "feat",
      "message": ": polish onboarding UX and tests",
      "repo": "agendate-ya-admin",
      "repo_display": "AgendateYa Admin",
      "timestamp": "2026-05-27T11:39:19-03:00"
    },
    {
      "hash": "3153bd1",
      "type": "feat",
      "message": ": polish onboarding UX and tests",
      "repo": "agendate-ya-admin",
      "repo_display": "AgendateYa Admin",
      "timestamp": "2026-05-27T11:34:29-03:00"
    },
    {
      "hash": "0a16f5e",
      "type": "feat",
      "message": ": add self-serve onboarding contract",
      "repo": "agendate-ya-admin",
      "repo_display": "AgendateYa Admin",
      "timestamp": "2026-05-27T11:15:53-03:00"
    },
    {
      "hash": "98eb9fe",
      "type": "feat",
      "message": ": add self-serve onboarding contract",
      "repo": "agendate-ya-admin",
      "repo_display": "AgendateYa Admin",
      "timestamp": "2026-05-27T11:12:10-03:00"
    },
    {
      "hash": "fc5c110",
      "type": "fix",
      "message": ": correct Kapso customer payload and reuse customer by external id",
      "repo": "agendate-ya",
      "repo_display": "AgendateYa",
      "timestamp": "2026-05-27T10:44:25-03:00"
    },
    {
      "hash": "c7e0a48",
      "type": "test",
      "message": ": cover whatsapp business journey",
      "repo": "agendate-ya-admin",
      "repo_display": "AgendateYa Admin",
      "timestamp": "2026-05-27T10:24:43-03:00"
    },
    {
      "hash": "1120518",
      "type": "test",
      "message": ": cover whatsapp business journey",
      "repo": "agendate-ya-admin",
      "repo_display": "AgendateYa Admin",
      "timestamp": "2026-05-27T10:20:56-03:00"
    },
    {
      "hash": "f2ff03d",
      "type": "feat",
      "message": ": add whatsapp business card",
      "repo": "agendate-ya-admin",
      "repo_display": "AgendateYa Admin",
      "timestamp": "2026-05-27T10:10:21-03:00"
    },
    {
      "hash": "2df1bb1",
      "type": "feat",
      "message": ": add Kapso provisioning webhook and number sync",
      "repo": "agendate-ya",
      "repo_display": "AgendateYa",
      "timestamp": "2026-05-27T10:02:25-03:00"
    },
    {
      "hash": "f0c9b68",
      "type": "feat",
      "message": ": add whatsapp business card",
      "repo": "agendate-ya-admin",
      "repo_display": "AgendateYa Admin",
      "timestamp": "2026-05-27T09:50:37-03:00"
    },
    {
      "hash": "35d8eea",
      "type": "feat",
      "message": ": add Kapso onboarding provider and self-serve start endpoint",
      "repo": "agendate-ya",
      "repo_display": "AgendateYa",
      "timestamp": "2026-05-27T09:33:24-03:00"
    },
    {
      "hash": "74b591d",
      "type": "feat",
      "message": ": add whatsapp business service contract",
      "repo": "agendate-ya-admin",
      "repo_display": "AgendateYa Admin",
      "timestamp": "2026-05-27T09:30:14-03:00"
    },
    {
      "hash": "6893543",
      "type": "feat",
      "message": ": add whatsapp business service contract",
      "repo": "agendate-ya-admin",
      "repo_display": "AgendateYa Admin",
      "timestamp": "2026-05-27T01:16:00-03:00"
    },
    {
      "hash": "adde868",
      "type": "feat",
      "message": ": add provider-neutral onboarding foundation",
      "repo": "agendate-ya",
      "repo_display": "AgendateYa",
      "timestamp": "2026-05-27T01:04:23-03:00"
    },
    {
      "hash": "e8832c2",
      "type": "fix",
      "message": "membership botton submite",
      "repo": "agendate-ya-admin",
      "repo_display": "AgendateYa Admin",
      "timestamp": "2026-05-26T23:32:08-03:00"
    }
  ]
}
